MemPlug/__init__.py
memplug-0.0.1.dist-info/METADATA
memplug-0.0.1.dist-info/WHEEL
memplug-0.0.1.dist-info/top_level.txt
memplug-0.0.1.dist-info/RECORD
