Metadata-Version: 2.4
Name: memplug
Version: 0.0.1
Summary: Memory Plug.
Requires-Python: >=3.8
